[
[
    {"label":"select","inputs":["coke"],"outputs":["ok"]}
    ,{"label":"coin","inputs":["50"],"outputs":["ok"]}
    ,{"label":"coin","inputs":["50"],"outputs":["ok"]}
    ,{"label":"vend","inputs":[],"outputs":["coke"]}
]
,[
    {"label":"select","inputs":["coke"],"outputs":["ok"]}
    ,{"label":"coin","inputs":["100"],"outputs":["ok"]}
    ,{"label":"vend","inputs":[],"outputs":["coke"]}
]
,[
    {"label":"select","inputs":["pepsi"],"outputs":["ok"]}
    ,{"label":"coin","inputs":["50"],"outputs":["ok"]}
    ,{"label":"coin","inputs":["50"],"outputs":["ok"]}
    ,{"label":"vend","inputs":[],"outputs":["pepsi"]}
]
]
